{
    "NaN": 0,
    "参考消息": 0,
    "深圳新闻网": 6,
    "凤凰网": 8,
    "文明网": 6,
    "正义网": 8,
    "东北网": 5,
    "韩国《中央日报》中文网": 6,
    "网易网": 8,
    "东方网": 7,
    "新浪网": 8,
    "第一财经": 7,
    "21世纪经济报道": 7,
    "重庆电视台": 6,
    "手机人民网": 9,
    "凯迪社区": 5,
    "中国外文出版发行事业局": 6,
    "德国之声中文网": 6,
    "猫扑社区": 2,
    "中国广播网": 8,
    "新加坡《联合早报》": 8,
    "多维新闻网": 7,
    "中国宁波网": 6,
    "中青网": 8,
    "凯风网": 4,
    "美国之音中文网": 7,
    "法广中文网": 7,
    "澎湃新闻网": 8,
    "光明网": 10,
    "人民网": 10,
    "中国江苏网": 7,
    "中国军网": 9,
    "中国日报网": 8,
    "英国《金融时报》": 7,
    "中国经济网": 8,
    "美国纽约时报中文版": 8,
    "福州新闻网": 6,
    "观察者网": 7,
    "天涯论坛": 3,
    "荆楚网": 5,
    "BBC中文网": 8,
    "搜狐网": 7,
    "海外网": 7,
    "日经中文网": 6,
    "杭州网": 5,
    "中国政府网": 8,
    "京报网": 8,
    "邯郸新闻网": 6,
    "中国网": 6,
    "新华网": 10,
    "经济参考报": 5,
    "南方网": 7,
    "中国经济网移动版": 7,
    "中国搜索": 7,
    "华尔街日报中文网": 8,
    "央视网": 7,
    "大众网": 5,
    "中国社会科学网": 6,
    "中国西藏网": 6,
    "界面网": 5,
    "华龙网": 5,
    "察网": 4,
    "人民网业务联盟": 6,
    "腾讯网": 8,
    "中国台湾网": 8,
    "中青在线": 7,
    "财新网": 8,
    "中国政协传媒网": 7,
    "财富网": 6,
    "国务院国有资产监督管理委员会网站": 9,
    "中国数字科技馆": 8,
    "齐鲁晚报": 6,
    "国家应急广播网": 8,
    "大洋网": 6,
    "荆州新闻网": 5
}